UART_clk_generator.v
module uart_clock_generator #(
    parameter DIV_WIDTH = 8   //sample_clk scale down factor 
)(
    input  wire        sys_clk,
    input  wire        rst_b,
    input  wire [2:0]  sel_baud_rate,

    output wire clk,
    output wire sample_clk
);


    reg [DIV_WIDTH-1:0] div256_cnt;

    always @(posedge sys_clk or negedge rst_b) begin
        if (!rst_b)
            div256_cnt <= 0;
        else
            div256_cnt <= div256_cnt + 1;
    end

    // These represent different baud rates
    wire tap0 = div256_cnt[0];
    wire tap1 = div256_cnt[1];
    wire tap2 = div256_cnt[2];
    wire tap3 = div256_cnt[3];
    wire tap4 = div256_cnt[4];
    wire tap5 = div256_cnt[5];
    wire tap6 = div256_cnt[6];
    wire tap7 = div256_cnt[7];

    reg mux_clk;

    always @(*) begin
        case (sel_baud_rate)
            3'd0: mux_clk = tap0;
            3'd1: mux_clk = tap1;
            3'd2: mux_clk = tap2;
            3'd3: mux_clk = tap3;
            3'd4: mux_clk = tap4;
            3'd5: mux_clk = tap5;
            3'd6: mux_clk = tap6;
            3'd7: mux_clk = tap7;
            default: mux_clk = tap3;
        endcase
    end

    assign sample_clk = mux_clk;

    reg [2:0] div8_cnt;

    always @(posedge sample_clk or negedge rst_b) begin
        if (!rst_b)
            div8_cnt <= 0;
        else
            div8_cnt <= div8_cnt + 1;
    end

    // MSB gives divide-by-8 clock
    assign clk = div8_cnt[2];

endmodule

tb_clk_generator.v
`timescale 1ns/1ps

module tb_uart_clock_generator;

    parameter CLK_PERIOD = 20; // 50 MHz → 20 ns

    reg sys_clk;
    reg rst_b;
    reg [2:0] sel_baud_rate;

    wire clk;         // baud clock
    wire sample_clk;  // 8× baud

    uart_clock_generator dut (
        .sys_clk(sys_clk),
        .rst_b(rst_b),
        .sel_baud_rate(sel_baud_rate),
        .clk(clk),
        .sample_clk(sample_clk)
    );
    
    initial begin
        $dumpfile("clk_generator_signal_dump.vcd");
        $dumpvars(0, tb_uart_clock_generator);
    end

    initial begin
        sys_clk = 0;
        forever #(CLK_PERIOD/2) sys_clk = ~sys_clk;
    end

    initial begin
        rst_b = 0;
        #100;
        rst_b = 1;
    end

    integer clk_edges;
    integer sample_edges;

    initial begin
        clk_edges = 0;
        sample_edges = 0;
    end

    always @(posedge clk)
        clk_edges = clk_edges + 1;

    always @(posedge sample_clk)
        sample_edges = sample_edges + 1;

    integer i;

    initial begin
        wait(rst_b);

        for (i = 0; i < 8; i = i + 1) begin
            sel_baud_rate = i;

            // reset counters
            clk_edges = 0;
            sample_edges = 0;

            // observe for some time
            #(100000);

            $display("SEL=%0d | clk_edges=%0d | sample_edges=%0d",
                     i, clk_edges, sample_edges);

            // -------------------------------------------------
            // Check relationship: sample_clk ≈ 8 × clk
            // -------------------------------------------------
            if (sample_edges < (clk_edges * 7) ||
                sample_edges > (clk_edges * 9)) begin
                $display("ERROR: Oversampling ratio incorrect for sel=%0d", i);
            end else begin
                $display("PASS: Oversampling ratio OK for sel=%0d", i);
            end

            $display("--------------------------------------");
        end

        $finish;
    end

endmodule

clk_generator_signal_dump.vcd
$date
	Fri Apr 10 16:17:01 2026
$end
$version
	Icarus Verilog
$end
$timescale
	1ps
$end
$scope module tb_uart_clock_generator $end
$var wire 1 ! sample_clk $end
$var wire 1 " clk $end
$var parameter 32 # CLK_PERIOD $end
$var reg 1 $ rst_b $end
$var reg 3 % sel_baud_rate [2:0] $end
$var reg 1 & sys_clk $end
$var integer 32 ' clk_edges [31:0] $end
$var integer 32 ( i [31:0] $end
$var integer 32 ) sample_edges [31:0] $end
$scope module dut $end
$var wire 1 $ rst_b $end
$var wire 1 ! sample_clk $end
$var wire 3 * sel_baud_rate [2:0] $end
$var wire 1 & sys_clk $end
$var wire 1 + tap7 $end
$var wire 1 , tap6 $end
$var wire 1 - tap5 $end
$var wire 1 . tap4 $end
$var wire 1 / tap3 $end
$var wire 1 0 tap2 $end
$var wire 1 1 tap1 $end
$var wire 1 2 tap0 $end
$var wire 1 " clk $end
$var parameter 32 3 DIV_WIDTH $end
$var reg 8 4 div256_cnt [7:0] $end
$var reg 3 5 div8_cnt [2:0] $end
$var reg 1 6 mux_clk $end
$upscope $end
$upscope $end
$enddefinitions $end
$comment Show the parameter values. $end
$dumpall
b1000 3
b10100 #
$end
#0
$dumpvars
06
b0 5
b0 4
02
01
00
0/
0.
0-
0,
0+
bx *
b0 )
bx (
b0 '
0&
bx %
0$
0"
0!
$end
#10000
1&
#20000
0&
#30000
1&
#40000
0&
#50000
1&
#60000
0&
#70000
1&
#80000
0&
#90000
1&
#100000
b0 %
b0 *
b0 (
0&
1$
#110000
b1 5
b1 )
1!
16
12
b1 4
1&
#120000
0&
#130000
0!
06
02
11
b10 4
1&
#140000
0&
#150000
b10 5
b10 )
1!
16
12
b11 4
1&
#160000
0&
#170000
0!
06
02
01
10
b100 4
1&
#180000
0&
#190000
b11 5
b11 )
1!
16
12
b101 4
1&
#200000
0&
#210000
0!
06
02
11
b110 4
1&
#220000
0&
#230000
b1 '
1"
b100 5
b100 )
1!
16
12
b111 4
1&
#240000
0&
#250000
0!
06
02
01
00
1/
b1000 4
1&
#260000
0&
#270000
b101 5
b101 )
1!
16
12
b1001 4
1&
#280000
0&
#290000
0!
06
02
11
b1010 4
1&
#300000
0&
#310000
b110 5
b110 )
1!
16
12
b1011 4
1&
#320000
0&
#330000
0!
06
02
01
10
b1100 4
1&
#340000
0&
#350000
b111 5
b111 )
1!
16
12
b1101 4
1&
#360000
0&
#370000
0!
06
02
11
b1110 4
1&
#380000
0&
#390000
0"
b0 5
b1000 )
1!
16
12
b1111 4
1&
#400000
0&
#410000
0!
06
02
01
00
0/
1.
b10000 4
1&
#420000
0&
#430000
b1 5
b1001 )
1!
16
12
b10001 4
1&
#440000
0&
#450000
0!
06
02
11
b10010 4
1&
#460000
0&
#470000
b10 5
b1010 )
1!
16
12
b10011 4
1&
#480000
0&
#490000
0!
06
02
01
10
b10100 4
1&
#500000
0&
#510000
b11 5
b1011 )
1!
16
12
b10101 4
1&
#520000
0&
#530000
0!
06
02
11
b10110 4
1&
#540000
0&
#550000
b10 '
1"
b100 5
b1100 )
1!
16
12
b10111 4
1&
#560000
0&
#570000
0!
06
02
01
00
1/
b11000 4
1&
#580000
0&
#590000
b101 5
b1101 )
1!
16
12
b11001 4
1&
#600000
0&
#610000
0!
06
02
11
b11010 4
1&
#620000
0&
#630000
b110 5
b1110 )
1!
16
12
b11011 4
1&
#640000
0&
#650000
0!
06
02
01
10
b11100 4
1&
#660000
0&
#670000
b111 5
b1111 )
1!
16
12
b11101 4
1&
#680000
0&
#690000
0!
06
02
11
b11110 4
1&
#700000
0&
#710000
0"
b0 5
b10000 )
1!
16
12
b11111 4
1&
#720000
0&
#730000
0!
06
02
01
00
0/
0.
1-
b100000 4
1&
#740000
0&
#750000
b1 5
b10001 )
1!
16
12
b100001 4
1&
#760000
0&
#770000
0!
06
02
11
b100010 4
1&
#780000
0&
#790000
b10 5
b10010 )
1!
16
12
b100011 4
1&
#800000
0&
#810000
0!
06
02
01
10
b100100 4
1&
#820000
0&
#830000
b11 5
b10011 )
1!
16
12
b100101 4
1&
#840000
0&
#850000
0!
06
02
11
b100110 4
1&
#860000
0&
#870000
b11 '
1"
b100 5
b10100 )
1!
16
12
b100111 4
1&
#880000
0&
#890000
0!
06
02
01
00
1/
b101000 4
1&
#900000
0&
#910000
b101 5
b10101 )
1!
16
12
b101001 4
1&
#920000
0&
#930000
0!
06
02
11
b101010 4
1&
#940000
0&
#950000
b110 5
b10110 )
1!
16
12
b101011 4
1&
#960000
0&
#970000
0!
06
02
01
10
b101100 4
1&
#980000
0&
#990000
b111 5
b10111 )
1!
16
12
b101101 4
1&
#1000000
0&
#1010000
0!
06
02
11
b101110 4
1&
#1020000
0&
#1030000
0"
b0 5
b11000 )
1!
16
12
b101111 4
1&
#1040000
0&
#1050000
0!
06
02
01
00
0/
1.
b110000 4
1&
#1060000
0&
#1070000
b1 5
b11001 )
1!
16
12
b110001 4
1&
#1080000
0&
#1090000
0!
06
02
11
b110010 4
1&
#1100000
0&
#1110000
b10 5
b11010 )
1!
16
12
b110011 4
1&
#1120000
0&
#1130000
0!
06
02
01
10
b110100 4
1&
#1140000
0&
#1150000
b11 5
b11011 )
1!
16
12
b110101 4
1&
#1160000
0&
#1170000
0!
06
02
11
b110110 4
1&
#1180000
0&
#1190000
b100 '
1"
b100 5
b11100 )
1!
16
12
b110111 4
1&
#1200000
0&
#1210000
0!
06
02
01
00
1/
b111000 4
1&
#1220000
0&
#1230000
b101 5
b11101 )
1!
16
12
b111001 4
1&
#1240000
0&
#1250000
0!
06
02
11
b111010 4
1&
#1260000
0&
#1270000
b110 5
b11110 )
1!
16
12
b111011 4
1&
#1280000
0&
#1290000
0!
06
02
01
10
b111100 4
1&
#1300000
0&
#1310000
b111 5
b11111 )
1!
16
12
b111101 4
1&
#1320000
0&
#1330000
0!
06
02
11
b111110 4
1&
#1340000
0&
#1350000
0"
b0 5
b100000 )
1!
16
12
b111111 4
1&
#1360000
0&
#1370000
0!
06
02
01
00
0/
0.
0-
1,
b1000000 4
1&
#1380000
0&
#1390000
b1 5
b100001 )
1!
16
12
b1000001 4
1&
#1400000
0&
#1410000
0!
06
02
11
b1000010 4
1&
#1420000
0&
#1430000
b10 5
b100010 )
1!
16
12
b1000011 4
1&
#1440000
0&
#1450000
0!
06
02
01
10
b1000100 4
1&
#1460000
0&
#1470000
b11 5
b100011 )
1!
16
12
b1000101 4
1&
#1480000
0&
#1490000
0!
06
02
11
b1000110 4
1&
#1500000
0&
#1510000
b101 '
1"
b100 5
b100100 )
1!
16
12
b1000111 4
1&
#1520000
0&
#1530000
0!
06
02
01
00
1/
b1001000 4
1&
#1540000
0&
#1550000
b101 5
b100101 )
1!
16
12
b1001001 4
1&
#1560000
0&
#1570000
0!
06
02
11
b1001010 4
1&
#1580000
0&
#1590000
b110 5
b100110 )
1!
16
12
b1001011 4
1&
#1600000
0&
#1610000
0!
06
02
01
10
b1001100 4
1&
#1620000
0&
#1630000
b111 5
b100111 )
1!
16
12
b1001101 4
1&
#1640000
0&
#1650000
0!
06
02
11
b1001110 4
1&
#1660000
0&
#1670000
0"
b0 5
b101000 )
1!
16
12
b1001111 4
1&
#1680000
0&
#1690000
0!
06
02
01
00
0/
1.
b1010000 4
1&
#1700000
0&
#1710000
b1 5
b101001 )
1!
16
12
b1010001 4
1&
#1720000
0&
#1730000
0!
06
02
11
b1010010 4
1&
#1740000
0&
#1750000
b10 5
b101010 )
1!
16
12
b1010011 4
1&
#1760000
0&
#1770000
0!
06
02
01
10
b1010100 4
1&
#1780000
0&
#1790000
b11 5
b101011 )
1!
16
12
b1010101 4
1&
#1800000
0&
#1810000
0!
06
02
11
b1010110 4
1&
#1820000
0&
#1830000
b110 '
1"
b100 5
b101100 )
1!
16
12
b1010111 4
1&
#1840000
0&
#1850000
0!
06
02
01
00
1/
b1011000 4
1&
#1860000
0&
#1870000
b101 5
b101101 )
1!
16
12
b1011001 4
1&
#1880000
0&
#1890000
0!
06
02
11
b1011010 4
1&
#1900000
0&
#1910000
b110 5
b101110 )
1!
16
12
b1011011 4
1&
#1920000
0&
#1930000
0!
06
02
01
10
b1011100 4
1&
#1940000
0&
#1950000
b111 5
b101111 )
1!
16
12
b1011101 4
1&
#1960000
0&
#1970000
0!
06
02
11
b1011110 4
1&
#1980000
0&
#1990000
0"
b0 5
b110000 )
1!
16
12
b1011111 4
1&
#2000000
0&
#2010000
0!
06
02
01
00
0/
0.
1-
b1100000 4
1&
#2020000
0&
#2030000
b1 5
b110001 )
1!
16
12
b1100001 4
1&
#2040000
0&
#2050000
0!
06
02
11
b1100010 4
1&
#2060000
0&
#2070000
b10 5
b110010 )
1!
16
12
b1100011 4
1&
#2080000
0&
#2090000
0!
06
02
01
10
b1100100 4
1&
#2100000
0&
#2110000
b11 5
b110011 )
1!
16
12
b1100101 4
1&
#2120000
0&
#2130000
0!
06
02
11
b1100110 4
1&
#2140000
0&
#2150000
b111 '
1"
b100 5
b110100 )
1!
16
12
b1100111 4
1&
#2160000
0&
#2170000
0!
06
02
01
00
1/
b1101000 4
1&
#2180000
0&
#2190000
b101 5
b110101 )
1!
16
12
b1101001 4
1&
#2200000
0&
#2210000
0!
06
02
11
b1101010 4
1&
#2220000
0&
#2230000
b110 5
b110110 )
1!
16
12
b1101011 4
1&
#2240000
0&
#2250000
0!
06
02
01
10
b1101100 4
1&
#2260000
0&
#2270000
b111 5
b110111 )
1!
16
12
b1101101 4
1&
#2280000
0&
#2290000
0!
06
02
11
b1101110 4
1&
#2300000
0&
#2310000
0"
b0 5
b111000 )
1!
16
12
b1101111 4
1&
#2320000
0&
#2330000
0!
06
02
01
00
0/
1.
b1110000 4
1&
#2340000
0&
#2350000
b1 5
b111001 )
1!
16
12
b1110001 4
1&
#2360000
0&
#2370000
0!
06
02
11
b1110010 4
1&
#2380000
0&
#2390000
b10 5
b111010 )
1!
16
12
b1110011 4
1&
#2400000
0&
#2410000
0!
06
02
01
10
b1110100 4
1&
#2420000
0&
#2430000
b11 5
b111011 )
1!
16
12
b1110101 4
1&
#2440000
0&
#2450000
0!
06
02
11
b1110110 4
1&
#2460000
0&
#2470000
b1000 '
1"
b100 5
b111100 )
1!
16
12
b1110111 4
1&
#2480000
0&
#2490000
0!
06
02
01
00
1/
b1111000 4
1&
#2500000
0&
#2510000
b101 5
b111101 )
1!
16
12
b1111001 4
1&
#2520000
0&
#2530000
0!
06
02
11
b1111010 4
1&
#2540000
0&
#2550000
b110 5
b111110 )
1!
16
12
b1111011 4
1&
#2560000
0&
#2570000
0!
06
02
01
10
b1111100 4
1&
#2580000
0&
#2590000
b111 5
b111111 )
1!
16
12
b1111101 4
1&
#2600000
0&
#2610000
0!
06
02
11
b1111110 4
1&
#2620000
0&
#2630000
0"
b0 5
b1000000 )
1!
16
12
b1111111 4
1&
#2640000
0&
#2650000
0!
06
02
01
00
0/
0.
0-
0,
1+
b10000000 4
1&
#2660000
0&
#2670000
b1 5
b1000001 )
1!
16
12
b10000001 4
1&
#2680000
0&
#2690000
0!
06
02
11
b10000010 4
1&
#2700000
0&
#2710000
b10 5
b1000010 )
1!
16
12
b10000011 4
1&
#2720000
0&
#2730000
0!
06
02
01
10
b10000100 4
1&
#2740000
0&
#2750000
b11 5
b1000011 )
1!
16
12
b10000101 4
1&
#2760000
0&
#2770000
0!
06
02
11
b10000110 4
1&
#2780000
0&
#2790000
b1001 '
1"
b100 5
b1000100 )
1!
16
12
b10000111 4
1&
#2800000
0&
#2810000
0!
06
02
01
00
1/
b10001000 4
1&
#2820000
0&
#2830000
b101 5
b1000101 )
1!
16
12
b10001001 4
1&
#2840000
0&
#2850000
0!
06
02
11
b10001010 4
1&
#2860000
0&
#2870000
b110 5
b1000110 )
1!
16
12
b10001011 4
1&
#2880000
0&
#2890000
0!
06
02
01
10
b10001100 4
1&
#2900000
0&
#2910000
b111 5
b1000111 )
1!
16
12
b10001101 4
1&
#2920000
0&
#2930000
0!
06
02
11
b10001110 4
1&
#2940000
0&
#2950000
0"
b0 5
b1001000 )
1!
16
12
b10001111 4
1&
#2960000
0&
#2970000
0!
06
02
01
00
0/
1.
b10010000 4
1&
#2980000
0&
#2990000
b1 5
b1001001 )
1!
16
12
b10010001 4
1&
#3000000
0&
#3010000
0!
06
02
11
b10010010 4
1&
#3020000
0&
#3030000
b10 5
b1001010 )
1!
16
12
b10010011 4
1&
#3040000
0&
#3050000
0!
06
02
01
10
b10010100 4
1&
#3060000
0&
#3070000
b11 5
b1001011 )
1!
16
12
b10010101 4
1&
#3080000
0&
#3090000
0!
06
02
11
b10010110 4
1&
#3100000
0&
#3110000
b1010 '
1"
b100 5
b1001100 )
1!
16
12
b10010111 4
1&
#3120000
0&
#3130000
0!
06
02
01
00
1/
b10011000 4
1&
#3140000
0&
#3150000
b101 5
b1001101 )
1!
16
12
b10011001 4
1&
#3160000
0&
#3170000
0!
06
02
11
b10011010 4
1&
#3180000
0&
#3190000
b110 5
b1001110 )
1!
16
12
b10011011 4
1&
#3200000
0&
#3210000
0!
06
02
01
10
b10011100 4
1&
#3220000
0&
#3230000
b111 5
b1001111 )
1!
16
12
b10011101 4
1&
#3240000
0&
#3250000
0!
06
02
11
b10011110 4
1&
#3260000
0&
#3270000
0"
b0 5
b1010000 )
1!
16
12
b10011111 4
1&
#3280000
0&
#3290000
0!
06
02
01
00
0/
0.
1-
b10100000 4
1&
#3300000
0&
#3310000
b1 5
b1010001 )
1!
16
12
b10100001 4
1&
#3320000
0&
#3330000
0!
06
02
11
b10100010 4
1&
#3340000
0&
#3350000
b10 5
b1010010 )
1!
16
12
b10100011 4
1&
#3360000
0&
#3370000
0!
06
02
01
10
b10100100 4
1&
#3380000
0&
#3390000
b11 5
b1010011 )
1!
16
12
b10100101 4
1&
#3400000
0&
#3410000
0!
06
02
11
b10100110 4
1&
#3420000
0&
#3430000
b1011 '
1"
b100 5
b1010100 )
1!
16
12
b10100111 4
1&
#3440000
0&
#3450000
0!
06
02
01
00
1/
b10101000 4
1&
#3460000
0&
#3470000
b101 5
b1010101 )
1!
16
12
b10101001 4
1&
#3480000
0&
#3490000
0!
06
02
11
b10101010 4
1&
#3500000
0&
#3510000
b110 5
b1010110 )
1!
16
12
b10101011 4
1&
#3520000
0&
#3530000
0!
06
02
01
10
b10101100 4
1&
#3540000
0&
#3550000
b111 5
b1010111 )
1!
16
12
b10101101 4
1&
#3560000
0&
#3570000
0!
06
02
11
b10101110 4
1&
#3580000
0&
#3590000
0"
b0 5
b1011000 )
1!
16
12
b10101111 4
1&
#3600000
0&
#3610000
0!
06
02
01
00
0/
1.
b10110000 4
1&
#3620000
0&
#3630000
b1 5
b1011001 )
1!
16
12
b10110001 4
1&
#3640000
0&
#3650000
0!
06
02
11
b10110010 4
1&
#3660000
0&
#3670000
b10 5
b1011010 )
1!
16
12
b10110011 4
1&
#3680000
0&
#3690000
0!
06
02
01
10
b10110100 4
1&
#3700000
0&
#3710000
b11 5
b1011011 )
1!
16
12
b10110101 4
1&
#3720000
0&
#3730000
0!
06
02
11
b10110110 4
1&
#3740000
0&
#3750000
b1100 '
1"
b100 5
b1011100 )
1!
16
12
b10110111 4
1&
#3760000
0&
#3770000
0!
06
02
01
00
1/
b10111000 4
1&
#3780000
0&
#3790000
b101 5
b1011101 )
1!
16
12
b10111001 4
1&
#3800000
0&
#3810000
0!
06
02
11
b10111010 4
1&
#3820000
0&
#3830000
b110 5
b1011110 )
1!
16
12
b10111011 4
1&
#3840000
0&
#3850000
0!
06
02
01
10
b10111100 4
1&
#3860000
0&
#3870000
b111 5
b1011111 )
1!
16
12
b10111101 4
1&
#3880000
0&
#3890000
0!
06
02
11
b10111110 4
1&
#3900000
0&
#3910000
0"
b0 5
b1100000 )
1!
16
12
b10111111 4
1&
#3920000
0&
#3930000
0!
06
02
01
00
0/
0.
0-
1,
b11000000 4
1&
#3940000
0&
#3950000
b1 5
b1100001 )
1!
16
12
b11000001 4
1&
#3960000
0&
#3970000
0!
06
02
11
b11000010 4
1&
#3980000
0&
#3990000
b10 5
b1100010 )
1!
16
12
b11000011 4
1&
#4000000
0&
#4010000
0!
06
02
01
10
b11000100 4
1&
#4020000
0&
#4030000
b11 5
b1100011 )
1!
16
12
b11000101 4
1&
#4040000
0&
#4050000
0!
06
02
11
b11000110 4
1&
#4060000
0&
#4070000
b1101 '
1"
b100 5
b1100100 )
1!
16
12
b11000111 4
1&
#4080000
0&
#4090000
0!
06
02
01
00
1/
b11001000 4
1&
#4100000
0&
#4110000
b101 5
b1100101 )
1!
16
12
b11001001 4
1&
#4120000
0&
#4130000
0!
06
02
11
b11001010 4
1&
#4140000
0&
#4150000
b110 5
b1100110 )
1!
16
12
b11001011 4
1&
#4160000
0&
#4170000
0!
06
02
01
10
b11001100 4
1&
#4180000
0&
#4190000
b111 5
b1100111 )
1!
16
12
b11001101 4
1&
#4200000
0&
#4210000
0!
06
02
11
b11001110 4
1&
#4220000
0&
#4230000
0"
b0 5
b1101000 )
1!
16
12
b11001111 4
1&
#4240000
0&
#4250000
0!
06
02
01
00
0/
1.
b11010000 4
1&
#4260000
0&
#4270000
b1 5
b1101001 )
1!
16
12
b11010001 4
1&
#4280000
0&
#4290000
0!
06
02
11
b11010010 4
1&
#4300000
0&
#4310000
b10 5
b1101010 )
1!
16
12
b11010011 4
1&
#4320000
0&
#4330000
0!
06
02
01
10
b11010100 4
1&
#4340000
0&
#4350000
b11 5
b1101011 )
1!
16
12
b11010101 4
1&
#4360000
0&
#4370000
0!
06
02
11
b11010110 4
1&
#4380000
0&
#4390000
b1110 '
1"
b100 5
b1101100 )
1!
16
12
b11010111 4
1&
#4400000
0&
#4410000
0!
06
02
01
00
1/
b11011000 4
1&
#4420000
0&
#4430000
b101 5
b1101101 )
1!
16
12
b11011001 4
1&
#4440000
0&
#4450000
0!
06
02
11
b11011010 4
1&
#4460000
0&
#4470000
b110 5
b1101110 )
1!
16
12
b11011011 4
1&
#4480000
0&
#4490000
0!
06
02
01
10
b11011100 4
1&
#4500000
0&
#4510000
b111 5
b1101111 )
1!
16
12
b11011101 4
1&
#4520000
0&
#4530000
0!
06
02
11
b11011110 4
1&
#4540000
0&
#4550000
0"
b0 5
b1110000 )
1!
16
12
b11011111 4
1&
#4560000
0&
#4570000
0!
06
02
01
00
0/
0.
1-
b11100000 4
1&
#4580000
0&
#4590000
b1 5
b1110001 )
1!
16
12
b11100001 4
1&
#4600000
0&
#4610000
0!
06
02
11
b11100010 4
1&
#4620000
0&
#4630000
b10 5
b1110010 )
1!
16
12
b11100011 4
1&
#4640000
0&
#4650000
0!
06
02
01
10
b11100100 4
1&
#4660000
0&
#4670000
b11 5
b1110011 )
1!
16
12
b11100101 4
1&
#4680000
0&
#4690000
0!
06
02
11
b11100110 4
1&
#4700000
0&
#4710000
b1111 '
1"
b100 5
b1110100 )
1!
16
12
b11100111 4
1&
#4720000
0&
#4730000
0!
06
02
01
00
1/
b11101000 4
1&
#4740000
0&
#4750000
b101 5
b1110101 )
1!
16
12
b11101001 4
1&
#4760000
0&
#4770000
0!
06
02
11
b11101010 4
1&
#4780000
0&
#4790000
b110 5
b1110110 )
1!
16
12
b11101011 4
1&
#4800000
0&
#4810000
0!
06
02
01
10
b11101100 4
1&
#4820000
0&
#4830000
b111 5
b1110111 )
1!
16
12
b11101101 4
1&
#4840000
0&
#4850000
0!
06
02
11
b11101110 4
1&
#4860000
0&
#4870000
0"
b0 5
b1111000 )
1!
16
12
b11101111 4
1&
#4880000
0&
#4890000
0!
06
02
01
00
0/
1.
b11110000 4
1&
#4900000
0&
#4910000
b1 5
b1111001 )
1!
16
12
b11110001 4
1&
#4920000
0&
#4930000
0!
06
02
11
b11110010 4
1&
#4940000
0&
#4950000
b10 5
b1111010 )
1!
16
12
b11110011 4
1&
#4960000
0&
#4970000
0!
06
02
01
10
b11110100 4
1&
#4980000
0&
#4990000
b11 5
b1111011 )
1!
16
12
b11110101 4
1&
#5000000
0&
#5010000
0!
06
02
11
b11110110 4
1&
#5020000
0&
#5030000
b10000 '
1"
b100 5
b1111100 )
1!
16
12
b11110111 4
1&
#5040000
0&
#5050000
0!
06
02
01
00
1/
b11111000 4
1&
#5060000
0&
#5070000
b101 5
b1111101 )
1!
16
12
b11111001 4
1&
#5080000
0&
#5090000
0!
06
02
11
b11111010 4
1&
#5100000
0&
#5110000
b110 5
b1111110 )
1!
16
12
b11111011 4
1&
#5120000
0&
#5130000
0!
06
02
01
10
b11111100 4
1&
#5140000
0&
#5150000
b111 5
b1111111 )
1!
16
12
b11111101 4
1&
#5160000
0&
#5170000
0!
06
02
11
b11111110 4
1&
#5180000
0&
#5190000
0"
b0 5
b10000000 )
1!
16
12
b11111111 4
1&
#5200000
0&
#5210000
0!
06
02
01
00
0/
0.
0-
0,
0+
b0 4
1&
#5220000
0&
#5230000
b1 5
b10000001 )
1!
16
12
b1 4
1&
#5240000
0&
#5250000
0!
06
02
11
b10 4
1&
#5260000
0&
#5270000
b10 5
b10000010 )
1!
16
12
b11 4
1&
#5280000
0&
#5290000
0!
06
02
01
10
b100 4
1&
#5300000
0&
#5310000
b11 5
b10000011 )
1!
16
12
b101 4
1&
#5320000
0&
#5330000
0!
06
02
11
b110 4
1&
#5340000
0&
#5350000
b10001 '
1"
b100 5
b10000100 )
1!
16
12
b111 4
1&
#5360000
0&
#5370000
0!
06
02
01
00
1/
b1000 4
1&
#5380000
0&
#5390000
b101 5
b10000101 )
1!
16
12
b1001 4
1&
#5400000
0&
#5410000
0!
06
02
11
b1010 4
1&
#5420000
0&
#5430000
b110 5
b10000110 )
1!
16
12
b1011 4
1&
#5440000
0&
#5450000
0!
06
02
01
10
b1100 4
1&
#5460000
0&
#5470000
b111 5
b10000111 )
1!
16
12
b1101 4
1&
#5480000
0&
#5490000
0!
06
02
11
b1110 4
1&
#5500000
0&
#5510000
0"
b0 5
b10001000 )
1!
16
12
b1111 4
1&
#5520000
0&
#5530000
0!
06
02
01
00
0/
1.
b10000 4
1&
#5540000
0&
#5550000
b1 5
b10001001 )
1!
16
12
b10001 4
1&
#5560000
0&
#5570000
0!
06
02
11
b10010 4
1&
#5580000
0&
#5590000
b10 5
b10001010 )
1!
16
12
b10011 4
1&
#5600000
0&
#5610000
0!
06
02
01
10
b10100 4
1&
#5620000
0&
#5630000
b11 5
b10001011 )
1!
16
12
b10101 4
1&
#5640000
0&
#5650000
0!
06
02
11
b10110 4
1&
#5660000
0&
#5670000
b10010 '
1"
b100 5
b10001100 )
1!
16
12
b10111 4
1&
#5680000
0&
#5690000
0!
06
02
01
00
1/
b11000 4
1&
#5700000
0&
#5710000
b101 5
b10001101 )
1!
16
12
b11001 4
1&
#5720000
0&
#5730000
0!
06
02
11
b11010 4
1&
#5740000
0&
#5750000
b110 5
b10001110 )
1!
16
12
b11011 4
1&
#5760000
0&
#5770000
0!
06
02
01
10
b11100 4
1&
#5780000
0&
#5790000
b111 5
b10001111 )
1!
16
12
b11101 4
1&
#5800000
0&
#5810000
0!
06
02
11
b11110 4
1&
#5820000
0&
#5830000
0"
b0 5
b10010000 )
1!
16
12
b11111 4
1&
#5840000
0&
#5850000
0!
06
02
01
00
0/
0.
1-
b100000 4
1&
#5860000
0&
#5870000
b1 5
b10010001 )
1!
16
12
b100001 4
1&
#5880000
0&
#5890000
0!
06
02
11
b100010 4
1&
#5900000
0&
#5910000
b10 5
b10010010 )
1!
16
12
b100011 4
1&
#5920000
0&
#5930000
0!
06
02
01
10
b100100 4
1&
#5940000
0&
#5950000
b11 5
b10010011 )
1!
16
12
b100101 4
1&
#5960000
0&
#5970000
0!
06
02
11
b100110 4
1&
#5980000
0&
#5990000
b10011 '
1"
b100 5
b10010100 )
1!
16
12
b100111 4
1&
#6000000
0&
#6010000
0!
06
02
01
00
1/
b101000 4
1&
#6020000
0&
#6030000
b101 5
b10010101 )
1!
16
12
b101001 4
1&
#6040000
0&
#6050000
0!
06
02
11
b101010 4
1&
#6060000
0&
#6070000
b110 5
b10010110 )
1!
16
12
b101011 4
1&
#6080000
0&
#6090000
0!
06
02
01
10
b101100 4
1&
#6100000
0&
#6110000
b111 5
b10010111 )
1!
16
12
b101101 4
1&
#6120000
0&
#6130000
0!
06
02
11
b101110 4
1&
#6140000
0&
#6150000
0"
b0 5
b10011000 )
1!
16
12
b101111 4
1&
#6160000
0&
#6170000
0!
06
02
01
00
0/
1.
b110000 4
1&
#6180000
0&
#6190000
b1 5
b10011001 )
1!
16
12
b110001 4
1&
#6200000
0&
#6210000
0!
06
02
11
b110010 4
1&
#6220000
0&
#6230000
b10 5
b10011010 )
1!
16
12
b110011 4
1&
#6240000
0&
#6250000
0!
06
02
01
10
b110100 4
1&
#6260000
0&
#6270000
b11 5
b10011011 )
1!
16
12
b110101 4
1&
#6280000
0&
#6290000
0!
06
02
11
b110110 4
1&
#6300000
0&
#6310000
b10100 '
1"
b100 5
b10011100 )
1!
16
12
b110111 4
1&
#6320000
0&
#6330000
0!
06
02
01
00
1/
b111000 4
1&
#6340000
0&
#6350000
b101 5
b10011101 )
1!
16
12
b111001 4
1&
#6360000
0&
#6370000
0!
06
02
11
b111010 4
1&
#6380000
0&
#6390000
b110 5
b10011110 )
1!
16
12
b111011 4
1&
#6400000
0&
#6410000
0!
06
02
01
10
b111100 4
1&
#6420000
0&
#6430000
b111 5
b10011111 )
1!
16
12
b111101 4
1&
#6440000
0&
#6450000
0!
06
02
11
b111110 4
1&
#6460000
0&
#6470000
0"
b0 5
b10100000 )
1!
16
12
b111111 4
1&
#6480000
0&
#6490000
0!
06
02
01
00
0/
0.
0-
1,
b1000000 4
1&
#6500000
0&
#6510000
b1 5
b10100001 )
1!
16
12
b1000001 4
1&
#6520000
0&
#6530000
0!
06
02
11
b1000010 4
1&
#6540000
0&
#6550000
b10 5
b10100010 )
1!
16
12
b1000011 4
1&
#6560000
0&
#6570000
0!
06
02
01
10
b1000100 4
1&
#6580000
0&
#6590000
b11 5
b10100011 )
1!
16
12
b1000101 4
1&
#6600000
0&
#6610000
0!
06
02
11
b1000110 4
1&
#6620000
0&
#6630000
b10101 '
1"
b100 5
b10100100 )
1!
16
12
b1000111 4
1&
#6640000
0&
#6650000
0!
06
02
01
00
1/
b1001000 4
1&
#6660000
0&
#6670000
b101 5
b10100101 )
1!
16
12
b1001001 4
1&
#6680000
0&
#6690000
0!
06
02
11
b1001010 4
1&
#6700000
0&
#6710000
b110 5
b10100110 )
1!
16
12
b1001011 4
1&
#6720000
0&
#6730000
0!
06
02
01
10
b1001100 4
1&
#6740000
0&
#6750000
b111 5
b10100111 )
1!
16
12
b1001101 4
1&
#6760000
0&
