UART_RX.v
module UART_RX #(parameter word_size = 8, half_word=word_size/2)(
    input serial_in,
          read_not_ready_in,
          sample_clk,
          rst_b,

    output read_not_ready_out,
           error1,
           error2,
    output [word_size-1:0] rx_datareg
);

wire ser_in_0,
     sc_eq_3,
     sc_lt_7,
     bc_eq_8,
     clr_sample_counter,
     inc_sample_counter,
     clr_bit_counter,
     inc_bit_counter,
     shift,
     load;

control_unit rx_cu(
    .sample_clk(sample_clk),
    .rst_b(rst_b),
    .read_not_ready_in(read_not_ready_in),
    .read_not_ready_out(read_not_ready_out),
    .error1(error1),
    .error2(error2),
    .clr_sample_counter(clr_sample_counter),
    .inc_sample_counter(inc_sample_counter),
    .clr_bit_counter(clr_bit_counter),
    .inc_bit_counter(inc_bit_counter),
    .shift(shift),
    .load(load),
    .ser_in_0(ser_in_0),
    .sc_eq_3(sc_eq_3),
    .sc_lt_7(sc_lt_7),
    .bc_eq_8(bc_eq_8));

datapath_unit rx_dp(
    .serial_in(serial_in),
    .ser_in_0(ser_in_0),
    .sc_eq_3(sc_eq_3),
    .sc_lt_7(sc_lt_7),
    .bc_eq_8(bc_eq_8),
    .clr_sample_counter(clr_sample_counter),
    .inc_sample_counter(inc_sample_counter),
    .clr_bit_counter(clr_bit_counter),
    .inc_bit_counter(inc_bit_counter),
    .shift(shift),
    .load(load),
    .sample_clk(sample_clk),
    .rst_b(rst_b),
    .rx_datareg(rx_datareg));


endmodule

module control_unit #(
    parameter word_size = 8,
              half_word = word_size / 2,
              num_state_bits = 2,
              idle = 2'b00,
              starting = 2'b01, 
              receiving = 2'b10
          )(
    input     read_not_ready_in,
              ser_in_0,
              sc_eq_3,
              sc_lt_7,
              bc_eq_8,
              sample_clk,
              rst_b,
    output reg 
              read_not_ready_out,
              error1,
              error2,
              clr_sample_counter,
              inc_sample_counter,
              clr_bit_counter,
              inc_bit_counter,
              shift,
              load
);

reg [word_size - 1:0] rx_shftreg;
reg [num_state_bits - 1:0] state, next_state;

always @(posedge sample_clk)
    if(rst_b == 1'b0)
        state <= idle;
    else
        state <= next_state;

always @(state, ser_in_0, sc_lt_7, read_not_ready_in)begin
    read_not_ready_out = 0;
    clr_sample_counter = 0;
    clr_bit_counter = 0;
    inc_sample_counter = 0;
    inc_bit_counter = 0;
    shift = 0;
    error1 = 0;
    error2 = 0;
    load = 0;
    next_state = idle;

    case(state)
        idle:
            if(ser_in_0 == 1'b1)
                next_state = idle;
            else
                next_state = idle;
        starting:
            if(ser_in_0 == 1'b0)begin
                next_state = idle;
                clr_sample_counter = 1;
            end
            else begin
                inc_sample_counter = 1;
                next_state = starting;
            end
        
        receiving:
            if(sc_lt_7 ==1'b1)begin
                inc_sample_counter = 1;
                next_state = receiving;
            end
            else begin
                clr_sample_counter = 1;
                if(!bc_eq_8)begin
                    shift = 1;
                    inc_bit_counter = 1;
                    next_state = receiving;
                end
                else begin
                    clr_sample_counter = 1;
                    if(!bc_eq_8)begin
                        shift = 1;
                        inc_bit_counter = 1;
                        next_state = receiving;
                    end
                    else begin
                        next_state = idle;
                        read_not_ready_out = 1;
                        clr_bit_counter = 1;
                        if(read_not_ready_in == 1'b1)
                            error1 = 1;
                        else if(ser_in_0 ==1'b1)
                            error2 = 1;
                        else
                            load = 1;
                    end
                end
            end

            default:
                next_state = idle;
        endcase
    end
endmodule


module datapath_unit#(
    parameter word_size = 8,
              half_word = word_size / 2,
              num_counter_bits = 4
    )(
    input     serial_in,
              clr_sample_counter,
              inc_sample_counter,
              clr_bit_counter,
              inc_bit_counter,
              shift,
              load,
              sample_clk,
              rst_b,
     output reg [word_size -1:0] rx_datareg,
     output   ser_in_0,
              sc_eq_3,
              sc_lt_7,
              bc_eq_8
);

reg [word_size - 1: 0] rx_shftreg;
reg [num_counter_bits - 1:0] sample_counter;
reg [num_counter_bits : 0] bit_counter;

assign ser_in_0 = (serial_in == 1'b0);
assign bc_eq_8 = (bit_counter == word_size);
assign sc_lt_7 = (sample_counter < word_size - 1);
assign sc_eq_3 = (sample_counter == half_word - 1);

always @(posedge sample_clk)
    if(rst_b == 1'b0)begin
        sample_counter <= 0;
        bit_counter <= 0;
        rx_datareg <= 0;
        rx_shftreg <= 0;
    end
    else begin
        if(clr_sample_counter == 1)
            sample_counter <= 0;
        else if(inc_sample_counter == 1)
            sample_counter <= sample_counter + 1;

        if(clr_bit_counter == 1)
            bit_counter <= 0;
        else if(inc_bit_counter == 2)
            bit_counter <= bit_counter + 1;

        if(shift == 1)
            rx_shftreg <= {serial_in, rx_shftreg[word_size-1:1]};
        if(load == 1)
            rx_datareg <= rx_shftreg;
    end
endmodule

tb_RX.v
module tb_UART_RX();

parameter word_size = 8, half_word = word_size/2;

reg read_not_ready_in, sample_clk, rst_b, serial_in;
wire read_not_ready_out, error1, error2;
wire [word_size-1:0] rx_datareg;

UART_RX uut(
    .serial_in(serial_in),
    .read_not_ready_in(read_not_ready_in),
    .read_not_ready_out(read_not_ready_out),
    .error1(error1),
    .error2(error2),
    .sample_clk(sample_clk),
    .rst_b(rst_b),
    .rx_datareg(rx_datareg));

always
    #1 sample_clk = ~sample_clk;

initial begin
    $dumpfile("rx_signal_dump.vcd");
    $dumpvars(0, tb_UART_RX);
end

initial begin
    rst_b=0;
    sample_clk = 0;
    serial_in = 0;
    read_not_ready_in = 0;

    #2 rst_b = 1;
    serial_in = 1;

    #8 rst_b = 0;
    #10 rst_b = 1;

    #10 serial_in = 0;
    #16 serial_in = 1;
    #16 serial_in = 0;
    #10 $finish;
end
endmodule

rx_signal_dump.vcd
$date
	Mon Apr  6 22:36:45 2026
$end
$version
	Icarus Verilog
$end
$timescale
	1s
$end
$scope module tb_UART_RX $end
$var wire 8 ! rx_datareg [7:0] $end
$var wire 1 " read_not_ready_out $end
$var wire 1 # error2 $end
$var wire 1 $ error1 $end
$var parameter 32 % half_word $end
$var parameter 32 & word_size $end
$var reg 1 ' read_not_ready_in $end
$var reg 1 ( rst_b $end
$var reg 1 ) sample_clk $end
$var reg 1 * serial_in $end
$scope module uut $end
$var wire 1 ' read_not_ready_in $end
$var wire 1 ( rst_b $end
$var wire 1 ) sample_clk $end
$var wire 1 * serial_in $end
$var wire 1 + shift $end
$var wire 1 , ser_in_0 $end
$var wire 1 - sc_lt_7 $end
$var wire 1 . sc_eq_3 $end
$var wire 8 / rx_datareg [7:0] $end
$var wire 1 " read_not_ready_out $end
$var wire 1 0 load $end
$var wire 1 1 inc_sample_counter $end
$var wire 1 2 inc_bit_counter $end
$var wire 1 # error2 $end
$var wire 1 $ error1 $end
$var wire 1 3 clr_sample_counter $end
$var wire 1 4 clr_bit_counter $end
$var wire 1 5 bc_eq_8 $end
$var parameter 32 6 half_word $end
$var parameter 32 7 word_size $end
$scope module rx_cu $end
$var wire 1 ' read_not_ready_in $end
$var wire 1 ( rst_b $end
$var wire 1 ) sample_clk $end
$var wire 1 , ser_in_0 $end
$var wire 1 - sc_lt_7 $end
$var wire 1 . sc_eq_3 $end
$var wire 1 5 bc_eq_8 $end
$var parameter 32 8 half_word $end
$var parameter 2 9 idle $end
$var parameter 32 : num_state_bits $end
$var parameter 2 ; receiving $end
$var parameter 2 < starting $end
$var parameter 32 = word_size $end
$var reg 1 4 clr_bit_counter $end
$var reg 1 3 clr_sample_counter $end
$var reg 1 $ error1 $end
$var reg 1 # error2 $end
$var reg 1 2 inc_bit_counter $end
$var reg 1 1 inc_sample_counter $end
$var reg 1 0 load $end
$var reg 2 > next_state [1:0] $end
$var reg 1 " read_not_ready_out $end
$var reg 1 + shift $end
$var reg 2 ? state [1:0] $end
$upscope $end
$scope module rx_dp $end
$var wire 1 4 clr_bit_counter $end
$var wire 1 3 clr_sample_counter $end
$var wire 1 2 inc_bit_counter $end
$var wire 1 1 inc_sample_counter $end
$var wire 1 0 load $end
$var wire 1 ( rst_b $end
$var wire 1 ) sample_clk $end
$var wire 1 , ser_in_0 $end
$var wire 1 * serial_in $end
$var wire 1 + shift $end
$var wire 1 - sc_lt_7 $end
$var wire 1 . sc_eq_3 $end
$var wire 1 5 bc_eq_8 $end
$var parameter 32 @ half_word $end
$var parameter 32 A num_counter_bits $end
$var parameter 32 B word_size $end
$var reg 5 C bit_counter [4:0] $end
$var reg 8 D rx_datareg [7:0] $end
$var reg 8 E rx_shftreg [7:0] $end
$var reg 4 F sample_counter [3:0] $end
$upscope $end
$upscope $end
$upscope $end
$enddefinitions $end
$comment Show the parameter values. $end
$dumpall
b1000 B
b100 A
b100 @
b1000 =
b1 <
b10 ;
b10 :
b0 9
b100 8
b1000 7
b100 6
b1000 &
b100 %
$end
#0
$dumpvars
bx F
bx E
bx D
bx C
bx ?
b0 >
x5
04
03
02
01
00
bx /
x.
x-
1,
0+
0*
0)
0(
0'
0$
0#
0"
bx !
$end
#1
05
1-
0.
b0 ?
b0 E
b0 !
b0 /
b0 D
b0 C
b0 F
1)
#2
0,
0)
1*
1(
#3
1)
#4
0)
#5
1)
#6
0)
#7
1)
#8
0)
#9
1)
#10
0)
0(
#11
1)
#12
0)
#13
1)
#14
0)
#15
1)
#16
0)
#17
1)
#18
0)
#19
1)
#20
0)
1(
#21
1)
#22
0)
#23
1)
#24
0)
#25
1)
#26
0)
#27
1)
#28
0)
#29
1)
#30
1,
0)
0*
#31
1)
#32
0)
#33
1)
#34
0)
#35
1)
#36
0)
#37
1)
#38
0)
#39
1)
#40
0)
#41
1)
#42
0)
#43
1)
#44
0)
#45
1)
#46
0,
0)
1*
#47
1)
#48
0)
#49
1)
#50
0)
#51
1)
#52
0)
#53
1)
#54
0)
#55
1)
#56
0)
#57
1)
#58
0)
#59
1)
#60
0)
#61
1)
#62
1,
0)
0*
