UART_TX.v
module UART_TX #(parameter word_size = 8)(
    input [word_size -1:0] data_bus,
    input load_tx_datareg,      //load data reg
          byte_ready,           //signal ready
          t_byte,               //signal tx start
          rst_b,                //resets internal regs
          clk,                 
    output serial_out
);

wire load_tx_DR, load_tx_SHFTREG, start, shift, clear, bc_lt_bcmax; 

control_unit tx_cu(
    .load_tx_DR(load_tx_DR),
    .load_tx_SHFTREG(load_tx_SHFTREG),
    .start(start),
    .shift(shift),
    .clear(clear),
    .load_tx_datareg(load_tx_datareg),
    .byte_ready(byte_ready),
    .t_byte(t_byte),
    .clk(clk),
    .rst_b(rst_b),
    .bc_lt_bcmax(bc_lt_bcmax));

datapath_unit tx_du(
    .load_tx_DR(load_tx_DR),
    .load_tx_SHFTREG(load_tx_SHFTREG),
    .start(start),
    .shift(shift),
    .clear(clear),
    .clk(clk),
    .rst_b(rst_b),
    .serial_out(serial_out),
    .bc_lt_bcmax(bc_lt_bcmax),
    .data_bus(data_bus));

endmodule


module control_unit #(
    parameter one_hot_count = 3,
              state_count = one_hot_count,
              size_bit_count = 3,

              idle = 3'b001,
              waiting = 3'b010,
              sending = 3'b100,
              all_ones = 9'b1_1111_1111
    )(
        input load_tx_datareg,      //load data reg
              byte_ready,           //signal ready
              t_byte,               //signal tx start
              rst_b,                //resets internal regs
              clk,
              bc_lt_bcmax,
        output reg load_tx_DR,
                   load_tx_SHFTREG,
                   start,
                   shift,
                   clear
);
reg [state_count-1:0] state, next_state;
always @(state, load_tx_datareg, byte_ready, t_byte, bc_lt_bcmax) begin:OUTPUT_AND_NEXT_STATE
    load_tx_DR = 0;
    load_tx_SHFTREG = 0;
    start = 0;
    shift = 0;
    clear = 0;
    next_state = idle;
    case(state)
        idle: if(load_tx_datareg == 1'b1)begin
            load_tx_DR = 1;
            next_state = idle;
        end
        else if(byte_ready == 1'b1)begin
            load_tx_SHFTREG = 1;
            next_state = waiting;
        end

        waiting: if(t_byte == 1)begin
            start = 1;
            next_state = sending;
        end
        else
            next_state = waiting;

        sending: if(bc_lt_bcmax)begin
            shift = 1;
            next_state = sending;
        end
        else begin
            clear = 1;
            next_state = idle;
        end

        default: next_state = idle;
    endcase
end

always @(posedge clk, negedge rst_b)begin:STATE_TRANSITIONS
    if(rst_b == 1'b0)
        state<=idle;
    else
        state<=next_state;
end

endmodule


module datapath_unit #(
    parameter word_size = 8,
              size_bit_count = 3,
              all_ones = {(word_size+1){1'b1}}
          )(
    input load_tx_DR,
          load_tx_SHFTREG,
          start,
          shift,
          clear,
          clk,
          rst_b,
    input [word_size-1:0] data_bus,

    output serial_out,
           bc_lt_bcmax
);

reg [word_size-1:0] tx_datareg;
reg [word_size:0] tx_shftreg;

reg [size_bit_count:0] bit_count;

assign serial_out = tx_shftreg[0];
assign bc_lt_bcmax = (bit_count < word_size + 1);

always @(posedge clk, negedge rst_b)
    if(rst_b == 0)begin
        tx_shftreg <= all_ones;
        bit_count <= 0;
    end
    else begin:REGISTER_TRANSFERS
        if(load_tx_DR == 1'b1)
            tx_datareg <= data_bus;

        if(load_tx_SHFTREG == 1'b1)
            tx_shftreg <= {tx_datareg, 1'b1};

        if(start == 1'b1)
            tx_shftreg[0] <= 0;

        if(clear == 1'b1)
            bit_count <= 0;

        if(shift == 1'b1)begin
            tx_shftreg <= {1'b1, tx_shftreg[word_size:1]};

            bit_count <= bit_count + 1;
        end
    end
endmodule

tb_TX.v
module tb_UART_tx();

reg load_tx_datareg, byte_ready, t_byte, clk, rst_b;
reg [7:0] data_bus;
wire serial_out;

UART_TX uut(.data_bus(data_bus),
            .load_tx_datareg(load_tx_datareg),
            .byte_ready(byte_ready),
            .t_byte(t_byte),
            .rst_b(rst_b), 
            .clk(clk)
);

always #5 clk = ~clk;

initial begin
    $dumpfile("signal_dump.vcd");
    $dumpvars(0, tb_UART_tx);
end

initial begin
    clk = 0;
    #5 rst_b = 0;
    data_bus[7:0] = 8'ha7;
    #5 rst_b = 1;
       load_tx_datareg = 0;
    #10 load_tx_datareg = 1; 
    #10 load_tx_datareg = 0; 
    #10 byte_ready = 1;
    #10 byte_ready = 0;
    #30 t_byte = 1;
    #5 data_bus = 8'h1a;
    #5 t_byte = 0;
       load_tx_datareg = 1;
    #10 load_tx_datareg = 0;
    #20 load_tx_datareg = 1;
    #5 data_bus = 8'hb4;
    #5 load_tx_datareg = 0;
    #80 $finish;
end
endmodule

signal_dump.vcd
$date
	Fri Apr  3 01:10:12 2026
$end
$version
	Icarus Verilog
$end
$timescale
	1s
$end
$scope module tb_UART_tx $end
$var reg 1 ! byte_ready $end
$var reg 1 " clk $end
$var reg 8 # data_bus [7:0] $end
$var reg 1 $ load_tx_datareg $end
$var reg 1 % rst_b $end
$var reg 1 & t_byte $end
$scope module uut $end
$var wire 1 ! byte_ready $end
$var wire 1 " clk $end
$var wire 8 ' data_bus [7:0] $end
$var wire 1 $ load_tx_datareg $end
$var wire 1 % rst_b $end
$var wire 1 & t_byte $end
$var wire 1 ( start $end
$var wire 1 ) shift $end
$var wire 1 * serial_out $end
$var wire 1 + load_tx_SHFTREG $end
$var wire 1 , load_tx_DR $end
$var wire 1 - clear $end
$var wire 1 . bc_lt_bcmax $end
$var parameter 32 / word_size $end
$scope module tx_cu $end
$var wire 1 ! byte_ready $end
$var wire 1 " clk $end
$var wire 1 $ load_tx_datareg $end
$var wire 1 % rst_b $end
$var wire 1 & t_byte $end
$var wire 1 . bc_lt_bcmax $end
$var parameter 9 0 all_ones $end
$var parameter 3 1 idle $end
$var parameter 32 2 one_hot_count $end
$var parameter 3 3 sending $end
$var parameter 32 4 size_bit_count $end
$var parameter 32 5 state_count $end
$var parameter 3 6 waiting $end
$var reg 1 - clear $end
$var reg 1 , load_tx_DR $end
$var reg 1 + load_tx_SHFTREG $end
$var reg 3 7 next_state [2:0] $end
$var reg 1 ) shift $end
$var reg 1 ( start $end
$var reg 3 8 state [2:0] $end
$scope begin OUTPUT_AND_NEXT_STATE $end
$upscope $end
$scope begin STATE_TRANSITIONS $end
$upscope $end
$upscope $end
$scope module tx_du $end
$var wire 1 - clear $end
$var wire 1 " clk $end
$var wire 8 9 data_bus [7:0] $end
$var wire 1 , load_tx_DR $end
$var wire 1 + load_tx_SHFTREG $end
$var wire 1 % rst_b $end
$var wire 1 ) shift $end
$var wire 1 ( start $end
$var wire 1 * serial_out $end
$var wire 1 . bc_lt_bcmax $end
$var parameter 9 : all_ones $end
$var parameter 32 ; size_bit_count $end
$var parameter 32 < word_size $end
$var reg 4 = bit_count [3:0] $end
$var reg 8 > tx_datareg [7:0] $end
$var reg 9 ? tx_shftreg [8:0] $end
$scope begin REGISTER_TRANSFERS $end
$upscope $end
$upscope $end
$upscope $end
$upscope $end
$enddefinitions $end
$comment Show the parameter values. $end
$dumpall
b1000 <
b11 ;
b111111111 :
b10 6
b11 5
b11 4
b100 3
b11 2
b1 1
b111111111 0
b1000 /
$end
#0
$dumpvars
bx ?
bx >
bx =
bx 9
bx 8
bx 7
x.
x-
x,
x+
x*
x)
x(
bx '
x&
x%
x$
bx #
0"
x!
$end
#5
b1 7
0-
0)
0(
0+
0,
1.
1*
b1 8
b0 =
b111111111 ?
b10100111 #
b10100111 '
b10100111 9
0%
1"
#10
0$
1%
0"
#15
1"
#20
1,
0"
1$
#25
b10100111 >
1"
#30
0,
0"
0$
#35
1"
#40
b10 7
1+
0"
1!
#45
b10 7
0+
b10 8
b101001111 ?
1"
#50
b10 7
0"
0!
#55
1"
#60
0"
#65
1"
#70
0"
#75
1"
#80
1(
b100 7
0"
1&
#85
1)
b100 7
0(
0*
b100 8
b101001110 ?
1"
b11010 #
b11010 '
b11010 9
#90
b100 7
1)
0"
1$
0&
#95
1*
b1 =
b110100111 ?
1"
#100
b100 7
1)
0"
0$
#105
b10 =
b111010011 ?
1"
#110
0"
#115
b11 =
b111101001 ?
1"
#120
b100 7
1)
0"
1$
#125
0*
b100 =
b111110100 ?
1"
b10110100 #
b10110100 '
b10110100 9
#130
b100 7
1)
0"
0$
#135
b101 =
b111111010 ?
1"
#140
0"
#145
1*
b110 =
b111111101 ?
1"
#150
0"
#155
0*
b111 =
b111111110 ?
1"
#160
0"
#165
1*
b1000 =
b111111111 ?
1"
#170
0"
#175
1-
b1 7
0)
0.
b1001 =
1"
#180
0"
#185
0-
1.
b1 8
b0 =
1"
